agspiel/__init__.py
agspiel/api/__init__.py
agspiel/api/ag.py
agspiel/api/aktie.py
agspiel/api/anleihe.py
agspiel/api/api.py
agspiel/api/ceo.py
agspiel/api/data.py
agspiel/api/historic_ag.py
agspiel/api/index.py
agspiel/api/kapitalmassnahme.py
agspiel/api/markt.py
agspiel/api/order.py
agspiel/api/zertifikat.py
agspiel/utils/__init__.py
agspiel/utils/controller.py
agspiel/utils/errors.py
agspiel/utils/main.py
tests/__init__.py
tests/test_ag.py
tests/test_api.py
tests/test_historic_ag.py
tests/test_markt.py
agspiel_python_api-0.5.7.dist-info/LICENSE
agspiel_python_api-0.5.7.dist-info/METADATA
agspiel_python_api-0.5.7.dist-info/WHEEL
agspiel_python_api-0.5.7.dist-info/top_level.txt
agspiel_python_api-0.5.7.dist-info/RECORD
