Metadata-Version: 2.1
Name: agspiel-python-api
Version: 0.5.7
Summary: Python API für das AG-Spiel
Home-page: https://github.com/KingKevin23/agspiel-python-api
Author: KingKevin23
Author-email: code@kingkevin.de
License: MIT License
Platform: UNKNOWN
Classifier: Programming Language :: Python :: 3
Classifier: License :: OSI Approved :: MIT License
Classifier: Operating System :: OS Independent
Requires-Python: >=3.8
License-File: LICENSE
Requires-Dist: requests (>=2.24.0)
Requires-Dist: beautifulsoup4 (>=4.9.1)
